tfe/__init__.py
tfe/initializers/__init__.py
tfe/initializers/initializers.py
tfe/layers/__init__.py
tfe/layers/convolutional.py
tfe-0.0.4.dist-info/LICENSE
tfe-0.0.4.dist-info/METADATA
tfe-0.0.4.dist-info/WHEEL
tfe-0.0.4.dist-info/top_level.txt
tfe-0.0.4.dist-info/RECORD
