Metadata-Version: 2.1
Name: tfe
Version: 0.0.4
Summary: TensorFlow Extras
Author-email: Matthew So <matthewclso@gmail.com>
Project-URL: Homepage, https://github.com/matthewclso/tfe
Project-URL: Bug Tracker, https://github.com/matthewclso/tfe/issues
Classifier: Programming Language :: Python :: 3
Classifier: License :: OSI Approved :: MIT License
Classifier: Operating System :: OS Independent
Requires-Python: >=3.7
License-File: LICENSE
